whitetower/__init__.py
whitetower/callbacks.py
whitetower/whitetower.py
whitetower/docker/__init__.py
whitetower/docker/docker_compose.py
whitetower/repositories/__init__.py
whitetower/repositories/ecr_repository.py
whitetower/repositories/repository.py
whitetower/types/__init__.py
whitetower/types/app_image_info.py
whitetower/types/image.py
whitetower/types/update_decision.py
whitetower-0.2.dist-info/METADATA
whitetower-0.2.dist-info/WHEEL
whitetower-0.2.dist-info/top_level.txt
whitetower-0.2.dist-info/RECORD
